{
  "title": "ZTE Blade V80 Pro",
  "brand": "ZTE",
  "category": "Smartphones",
  "added_on": "21st, Nov, 2025",
  "status": "AVAILABLE",
  "announced_date": "2025, November",
  "expected_release": "2025, December",
  "price": {
    "local_currency": "BDT",
    "amount": 0,
    "note": ""
  },
  "Camera": {
    "Dual:": "108 MP, f/1.8, (wide), PDAF Auxiliary lenses",
    "Features:": "LED flash, HDR, panorama",
    "Video:": "1080p@30fps",
    "Single:": "16 MP"
  },
  "Design": {
    "Dimensions:": "166 x 79 x 7.7 mm (6.54 x 3.11 x 0.30 in)",
    "Weight:": "195 g (6.88 oz)",
    "Build:": "Glass front, plastic frame",
    "SIM:": "Nano-SIM + Nano-SIM",
    "Others:": "IP64 dust tight and water resistant (water splashes)"
  },
  "Battery": {
    "Type:": "Non-removable Li-Po",
    "Capacity:": "5000 mAh",
    "Charging:": "22.5W wired 10W reverse wired"
  },
  "Display": {
    "Type:": "IPS LCD, 120Hz, 1000 nits (HBM)",
    "Size:": "6.75 inches, 112.2 cm2 (~85.6% screen-to-body ratio)",
    "Resolution:": "900 x 1940 pixels, 19.5:9 ratio (~317 ppi density)"
  },
  "Cellular": {
    "Technology:": "GSM / HSPA / LTE",
    "2G bands:": "GSM 850 / 900 / 1800 / 1900",
    "3G bands:": "HSDPA 850 / 900 / 1900 / 2100",
    "4G bands:": "LTE",
    "Speed:": "HSPA, LTE"
  },
  "Hardware": {
    "OS:": "Android 16",
    "Chipset:": "Unisoc T7280 (12 nm)",
    "CPU:": "Octa-core (2x2.2 GHz Cortex-A75 & 6x2.0 GHz Cortex-A55)",
    "GPU:": "Mali-G57 MP1",
    "Card slot:": "microSDXC",
    "Internal:": "256 GB",
    "RAM:": "8 GB",
    "Variant:": "8GB 256GB"
  },
  "Multimedia": {
    "Loudspeaker:": "Yes",
    "3.5mm jack:": "Yes"
  },
  "Connectivity & Features": {
    "WLAN:": "Wi-Fi 802.11 a/b/g/n/ac, dual-band",
    "Bluetooth:": "5.2, A2DP, LE",
    "GPS:": "GPS, GALILEO, GLONASS",
    "NFC:": "Unspecified",
    "FM radio:": "Unspecified",
    "USB:": "USB Type-C 2.0, OTG",
    "Sensors:": "Fingerprint (side-mounted), accelerometer, proximity, compass"
  }
}